odoo/addons/l10n_es_facturae_special_payment/README.rst
odoo/addons/l10n_es_facturae_special_payment/__init__.py
odoo/addons/l10n_es_facturae_special_payment/__manifest__.py
odoo/addons/l10n_es_facturae_special_payment/i18n/l10n_es_facturae_special_payment.pot
odoo/addons/l10n_es_facturae_special_payment/models/__init__.py
odoo/addons/l10n_es_facturae_special_payment/models/account_move.py
odoo/addons/l10n_es_facturae_special_payment/readme/CONTRIBUTORS.md
odoo/addons/l10n_es_facturae_special_payment/readme/DESCRIPTION.md
odoo/addons/l10n_es_facturae_special_payment/static/description/icon.png
odoo/addons/l10n_es_facturae_special_payment/static/description/index.html
odoo/addons/l10n_es_facturae_special_payment/tests/__init__.py
odoo/addons/l10n_es_facturae_special_payment/tests/test_common.py
odoo/addons/l10n_es_facturae_special_payment/views/account_move_view.xml
odoo/addons/l10n_es_facturae_special_payment/views/report_facturae.xml
odoo_addon_l10n_es_facturae_special_payment-17.0.1.1.0.dist-info/METADATA
odoo_addon_l10n_es_facturae_special_payment-17.0.1.1.0.dist-info/WHEEL
odoo_addon_l10n_es_facturae_special_payment-17.0.1.1.0.dist-info/top_level.txt
odoo_addon_l10n_es_facturae_special_payment-17.0.1.1.0.dist-info/RECORD
